MANIFEST.in
README.md
setup.py
django_lightapi.egg-info/PKG-INFO
django_lightapi.egg-info/SOURCES.txt
django_lightapi.egg-info/dependency_links.txt
django_lightapi.egg-info/requires.txt
django_lightapi.egg-info/top_level.txt
lightapi/__init__.py
lightapi/client.py
lightapi/value_utils.py
lightapi/cache/__init__.py
lightapi/cache/django.py
lightapi/crypto/RSA.py
lightapi/crypto/__init__.py
lightapi/crypto/client.py
lightapi/crypto/mixins.py
lightapi/django/__init__.py
lightapi/django/shortcuts.py
lightapi/django/urls.py
lightapi/django/views/__init__.py
lightapi/django/views/base.py
lightapi/django/views/crypto.py
lightapi/django/views/error.py