Metadata-Version: 1.0
Name: django-lightapi
Version: 0.108
Summary: django-lightapi is a super light weight api framework for exposing restful django webservices
Home-page: https://github.com/ulfur/django-lightapi
Author: Úlfur Kristjánsson
Author-email: ulfur@theawesometastic.com
License: UNKNOWN
Platform: UNKNOWN
